dagster_fmt/__init__.py
dagster_fmt/__main__.py
dagster_fmt/ops/__init__.py
dagster_fmt/ops/run_function.py
dagster_fmt/resources/__init__.py
dagster_fmt/shared/__init__.py
dagster_fmt/shared/create_decorator.py
dagster_fmt/shared/docstrings.py
dagster_fmt/shared/insert.py
dagster_fmt/shared/read_context.py
dagster_fmt/tool/__init__.py
dagster_fmt/tool/schema.py
dagster_fmt-0.0.4.dist-info/entry_points.txt
dagster_fmt-0.0.4.dist-info/LICENSE
dagster_fmt-0.0.4.dist-info/WHEEL
dagster_fmt-0.0.4.dist-info/METADATA
dagster_fmt-0.0.4.dist-info/RECORD
