Metadata-Version: 2.1
Name: dagster-fmt
Version: 0.0.4
Summary: Dagster code gen tool
Home-page: https://www.github.com/alrudolph/dagster_fmt
License: MIT
Author: arudolph
Author-email: alex3rudolph@gmail.com
Requires-Python: >=3.8,<4.0
Classifier: License :: OSI Approved :: MIT License
Classifier: Programming Language :: Python :: 3
Classifier: Programming Language :: Python :: 3.10
Classifier: Programming Language :: Python :: 3.8
Classifier: Programming Language :: Python :: 3.9
Requires-Dist: black (>=22.6.0,<23.0.0)
Requires-Dist: isort (>=5.10.1,<6.0.0)
Requires-Dist: toml (>=0.10.2,<0.11.0)
Project-URL: Repository, https://www.github.com/alrudolph/dagster_fmt
